{
  "parent": "tid:layer_1/find_loot_stronghold2",
  "display": {
    "icon": {
      "item": "minecraft:map"
    },
    "title": "Subterranean Cartographer",
    "description": "Craft a map out of eight paper and a compass",
    "frame": "task",
    "show_toast": true,
    "announce_to_chat": true,
    "hidden": false
  },
  "criteria": {
    "got_item": {
      "trigger": "minecraft:inventory_changed",
      "conditions": {
        "items": [
          {
            "item": "minecraft:map"
          }
        ]
      }
    }
  },
  "requirements": [
    [
      "got_item"
    ]
  ]
}